{
  "meta": {
    "game_name": "textmapworld_specificroom",
    "experiment_name": "far",
    "game_id": 20,
    "player_name": "Player 2",
    "game_role": "PathDescriber",
    "model_name": "programmatic",
    "round_count": 6,
    "completed": true
  },
  "calls": [
    {
      "round": 0,
      "call": {
        "timestamp": "2026-07-09T08:10:23.727582",
        "manipulated_prompt_obj": {},
        "raw_response_obj": {}
      }
    },
    {
      "round": 1,
      "call": {
        "timestamp": "2026-07-09T08:10:24.699950",
        "manipulated_prompt_obj": {},
        "raw_response_obj": {}
      }
    },
    {
      "round": 2,
      "call": {
        "timestamp": "2026-07-09T08:10:25.660135",
        "manipulated_prompt_obj": {},
        "raw_response_obj": {}
      }
    },
    {
      "round": 3,
      "call": {
        "timestamp": "2026-07-09T08:10:26.576770",
        "manipulated_prompt_obj": {},
        "raw_response_obj": {}
      }
    },
    {
      "round": 4,
      "call": {
        "timestamp": "2026-07-09T08:10:27.103366",
        "manipulated_prompt_obj": {},
        "raw_response_obj": {}
      }
    }
  ]
}