{
  "game_id": 258,
  "input": "Please write a summary of the following advertiser page: \"We insist on having the most talented team of web developers, content writers, graphic designers and online marketers in the industry. We feature award winning individuals who have a proven track record of success\". Use markdowns and target moms. Your answer must contain exactly 4 bullet points in markdown format and cannot contain commas.",
  "target": {
    "detectable_format:number_bullet_lists": {
      "num_bullets": 4
    },
    "punctuation:no_comma": {}
  }
}