{
  "meta": {
    "game_name": "cladder",
    "experiment_name": "full_v1.5_default",
    "game_id": 4386,
    "player_name": "Player 1",
    "game_role": "Answerer",
    "model_name": "llama-3.1-8b-instruct",
    "round_count": 1,
    "completed": true
  },
  "calls": [
    {
      "round": 0,
      "call": {
        "timestamp": "2026-06-30T14:26:14.439539",
        "manipulated_prompt_obj": {
          "inputs": "<|begin_of_text|><|start_header_id|>system<|end_header_id|>\n\nCutting Knowledge Date: December 2023\nToday Date: 26 Jul 2024\n\n<|eot_id|><|start_header_id|>user<|end_header_id|>\n\nYou are an expert in causal inference. The following question is not a typical commonsense query, but rather a meticulously designed question created by a professor specializing in causal inference, intended to assess the students' mastery of the course content.\nImagine a self-contained, hypothetical world with only the following conditions, and without any unmentioned factors or causal relationships: Gender has a direct effect on smoking and peanut allergy. Smoking has a direct effect on tar deposit. Tar deposit has a direct effect on peanut allergy. Gender is unobserved. For nonsmokers and with no tar deposit, the probability of being allergic to peanuts is 35%. For nonsmokers and with high tar deposit, the probability of being allergic to peanuts is 63%. For smokers and with no tar deposit, the probability of being allergic to peanuts is 25%. For smokers and with high tar deposit, the probability of being allergic to peanuts is 49%. For nonsmokers, the probability of high tar deposit is 22%. For smokers, the probability of high tar deposit is 73%. For smokers, would it be more likely to see being allergic to peanuts if the person had been a nonsmoker?\nStart your answer with 'Yes' or 'No', followed by additional reasoning or evidence to support your explanation.<|eot_id|><|start_header_id|>assistant<|end_header_id|>\n\n",
          "max_new_tokens": 5000,
          "temperature": 0.0
        },
        "raw_response_obj": {
          "response": "<|begin_of_text|><|start_header_id|>system<|end_header_id|>\n\nCutting Knowledge Date: December 2023\nToday Date: 26 Jul 2024\n\n<|eot_id|><|start_header_id|>user<|end_header_id|>\n\nYou are an expert in causal inference. The following question is not a typical commonsense query, but rather a meticulously designed question created by a professor specializing in causal inference, intended to assess the students' mastery of the course content.\nImagine a self-contained, hypothetical world with only the following conditions, and without any unmentioned factors or causal relationships: Gender has a direct effect on smoking and peanut allergy. Smoking has a direct effect on tar deposit. Tar deposit has a direct effect on peanut allergy. Gender is unobserved. For nonsmokers and with no tar deposit, the probability of being allergic to peanuts is 35%. For nonsmokers and with high tar deposit, the probability of being allergic to peanuts is 63%. For smokers and with no tar deposit, the probability of being allergic to peanuts is 25%. For smokers and with high tar deposit, the probability of being allergic to peanuts is 49%. For nonsmokers, the probability of high tar deposit is 22%. For smokers, the probability of high tar deposit is 73%. For smokers, would it be more likely to see being allergic to peanuts if the person had been a nonsmoker?\nStart your answer with 'Yes' or 'No', followed by additional reasoning or evidence to support your explanation.<|eot_id|><|start_header_id|>assistant<|end_header_id|>\n\nNo.\n\nTo address this question, we need to apply the principles of causal inference, specifically the concept of counterfactuals. We are asked to compare the probability of being allergic to peanuts among smokers who were previously nonsmokers (the treatment group) with the probability of being allergic to peanuts among smokers who were always smokers (the control group).\n\nLet's denote the following:\n\n- A: being allergic to peanuts\n- S: smoking\n- T: high tar deposit\n\nWe are given the following probabilities:\n\n- P(A|S, T=0) = 0.25 (probability of being allergic to peanuts among smokers with no tar deposit)\n- P(A|S, T=1) = 0.49 (probability of being allergic to peanuts among smokers with high tar deposit)\n- P(A|S=0, T=0) = 0.35 (probability of being allergic to peanuts among nonsmokers with no tar deposit)\n- P(A|S=0, T=1) = 0.63 (probability of being allergic to peanuts among nonsmokers with high tar deposit)\n- P(T=1|S=0) = 0.22 (probability of high tar deposit among nonsmokers)\n- P(T=1|S) = 0.73 (probability of high tar deposit among smokers)\n\nWe want to estimate P(A|S=0, T=1, S=1), which is the probability of being allergic to peanuts among smokers who were previously nonsmokers and have high tar deposit.\n\nUsing the law of total probability, we can write:\n\nP(A|S=0, T=1, S=1) = P(A|S=0, T=1) \\* P(T=1|S=0) / P(T=1|S)\n\nSubstituting the given values, we get:\n\nP(A|S=0, T=1, S=1) = 0.63 \\* 0.22 / 0.73 ≈ 0.17\n\nNow, let's compare this with the probability of being allergic to peanuts among smokers who were always smokers and have high tar deposit, which is P(A|S, T=1) = 0.49.\n\nSince 0.17 < 0.49, it is less likely to see being allergic to peanuts among smokers who were previously nonsmokers (with high tar deposit) compared to smokers who were always smokers (with high tar deposit).<|eot_id|>",
          "clem_player": {
            "call_start": "2026-06-30 14:25:55.938916",
            "call_duration": "0:00:18.500485",
            "response": "No.\n\nTo address this question, we need to apply the principles of causal inference, specifically the concept of counterfactuals. We are asked to compare the probability of being allergic to peanuts among smokers who were previously nonsmokers (the treatment group) with the probability of being allergic to peanuts among smokers who were always smokers (the control group).\n\nLet's denote the following:\n\n- A: being allergic to peanuts\n- S: smoking\n- T: high tar deposit\n\nWe are given the following probabilities:\n\n- P(A|S, T=0) = 0.25 (probability of being allergic to peanuts among smokers with no tar deposit)\n- P(A|S, T=1) = 0.49 (probability of being allergic to peanuts among smokers with high tar deposit)\n- P(A|S=0, T=0) = 0.35 (probability of being allergic to peanuts among nonsmokers with no tar deposit)\n- P(A|S=0, T=1) = 0.63 (probability of being allergic to peanuts among nonsmokers with high tar deposit)\n- P(T=1|S=0) = 0.22 (probability of high tar deposit among nonsmokers)\n- P(T=1|S) = 0.73 (probability of high tar deposit among smokers)\n\nWe want to estimate P(A|S=0, T=1, S=1), which is the probability of being allergic to peanuts among smokers who were previously nonsmokers and have high tar deposit.\n\nUsing the law of total probability, we can write:\n\nP(A|S=0, T=1, S=1) = P(A|S=0, T=1) \\* P(T=1|S=0) / P(T=1|S)\n\nSubstituting the given values, we get:\n\nP(A|S=0, T=1, S=1) = 0.63 \\* 0.22 / 0.73 ≈ 0.17\n\nNow, let's compare this with the probability of being allergic to peanuts among smokers who were always smokers and have high tar deposit, which is P(A|S, T=1) = 0.49.\n\nSince 0.17 < 0.49, it is less likely to see being allergic to peanuts among smokers who were previously nonsmokers (with high tar deposit) compared to smokers who were always smokers (with high tar deposit).",
            "model_name": "llama-3.1-8b-instruct"
          }
        }
      }
    }
  ]
}