{
  "meta": {
    "game_name": "codenames",
    "experiment_name": "unambiguous",
    "game_id": 5,
    "results_folder": "llama-3.1-8b-instruct",
    "clem_version": "3.7.2",
    "round_count": 7,
    "completed": true
  },
  "player_models": {
    "0": {
      "model_spec": {
        "model_name": "llama-3.1-8b-instruct",
        "_is_base_model": true,
        "backend": "huggingface_local",
        "context_size": "128k",
        "huggingface_id": "meta-llama/Llama-3.1-8B-Instruct",
        "languages": [
          "en",
          "de",
          "fr",
          "it",
          "pt",
          "hi",
          "es",
          "th"
        ],
        "license": {
          "name": "Meta",
          "url": "https://github.com/meta-llama/llama-models/blob/main/models/llama3_1/LICENSE"
        },
        "lookup_source": "/project/mmanina/lm-playschool-test-set/playpen/model_registry.json",
        "model_config": {
          "requires_api_key": false,
          "premade_chat_template": true,
          "eos_to_cull": "<\\|eot_id\\|>"
        },
        "open_weight": true,
        "parameters": "8B",
        "release_date": "2024-07-23"
      },
      "gen_args": {
        "temperature": 0.0,
        "max_tokens": 5000
      }
    }
  },
  "players": {
    "GM": {
      "game_role": "Game Master",
      "model_name": "programmatic"
    },
    "Player 1": {
      "game_role": "ClueGiver",
      "model_name": "llama-3.1-8b-instruct"
    },
    "Player 2": {
      "game_role": "Guesser",
      "model_name": "llama-3.1-8b-instruct"
    }
  },
  "turns": [
    [
      {
        "from": "GM",
        "to": "GM",
        "timestamp": "2026-06-30T14:14:44.654203",
        "action": {
          "type": "board status",
          "content": {
            "hidden": {
              "team": [
                "courtroom",
                "terrain",
                "sailboat",
                "greenhouse",
                "nomination",
                "bayou",
                "petroleum",
                "doorman",
                "migraine"
              ],
              "innocent": [
                "sincerity",
                "bacon",
                "riddance",
                "periscope",
                "vigilante",
                "apartment",
                "terrorism"
              ],
              "opponent": [
                "dime",
                "billboard",
                "mower",
                "bra",
                "weirdo",
                "burglary",
                "tanker",
                "nuisance"
              ],
              "assassin": [
                "bridesmaid"
              ]
            },
            "revealed": {
              "team": {
                "team": [],
                "innocent": [],
                "opponent": [],
                "assassin": []
              },
              "opponent": {
                "team": [],
                "innocent": [],
                "opponent": [],
                "assassin": []
              }
            }
          }
        }
      },
      {
        "from": "GM",
        "to": "Player 1",
        "timestamp": "2026-06-30T14:15:06.459551",
        "action": {
          "type": "send message",
          "content": "Provide one single-word clue that relates to some of your team's words from the list below. You can choose to how many and to which words your clue relates to.\nThe goal is to have your partner guess all of your team's words based on the clues you give them, before the other team has uncovered all of theirs. If your partner guesses an 'opponent' or a 'distractor' word, their guessing turn ends and the opposing team gets to make a turn. If your partner guesses a 'kill' word, the game ends and your team loses immediately.\nThe more words your clue relates to, the quicker you can win the game, but the harder the associations may be to guess for your partner, so choose your clue word wisely. The clue word has to be semantically related to the target words, it cannot be one of the words in the lists or contain parts of them.\n\nAlways give your single-word clue and your comma-separated list of related target words in the following format and make your answers as short as possible, never include any other text than is required in this form:\n\nCLUE: <WORD>\nTARGETS: <TARGETS>\n\nYour team words are: courtroom, terrain, sailboat, greenhouse, nomination, bayou, petroleum, doorman, migraine.\nYour opponent's team words are: dime, billboard, mower, bra, weirdo, burglary, tanker, nuisance.\nDistractor words are: sincerity, bacon, riddance, periscope, vigilante, apartment, terrorism.\nThe kill words are: bridesmaid.",
          "label": "context"
        }
      },
      {
        "from": "Player 1",
        "to": "GM",
        "timestamp": "2026-06-30T14:15:06.459568",
        "action": {
          "type": "get message",
          "content": "CLUE: judge\nTARGETS: courtroom, nomination, doorman",
          "label": "response"
        }
      },
      {
        "from": "GM",
        "to": "GM",
        "timestamp": "2026-06-30T14:15:06.459743",
        "action": {
          "type": "clue",
          "content": "judge"
        }
      },
      {
        "from": "GM",
        "to": "GM",
        "timestamp": "2026-06-30T14:15:06.459765",
        "action": {
          "type": "targets",
          "content": [
            "courtroom",
            "nomination",
            "doorman"
          ]
        }
      },
      {
        "from": "GM",
        "to": "GM",
        "timestamp": "2026-06-30T14:15:06.459785",
        "action": {
          "type": "word targeted",
          "content": {
            "word": "courtroom",
            "assignment": "team"
          }
        }
      },
      {
        "from": "GM",
        "to": "GM",
        "timestamp": "2026-06-30T14:15:06.459804",
        "action": {
          "type": "word targeted",
          "content": {
            "word": "nomination",
            "assignment": "team"
          }
        }
      },
      {
        "from": "GM",
        "to": "GM",
        "timestamp": "2026-06-30T14:15:06.459822",
        "action": {
          "type": "word targeted",
          "content": {
            "word": "doorman",
            "assignment": "team"
          }
        }
      },
      {
        "from": "GM",
        "to": "Player 2",
        "timestamp": "2026-06-30T14:15:27.182808",
        "action": {
          "type": "send message",
          "content": "Provide a comma-separated list of up to 3 words from the following list that best relate or are most closely associated with the word 'judge'. Always start your list of guess(es) with 'GUESS: ' and do not include any other text in your answer.\n\nsincerity, courtroom, greenhouse, doorman, nomination, migraine, sailboat, terrorism, terrain, nuisance, bayou, burglary, bridesmaid, apartment, periscope, dime, bra, mower, bacon, tanker, riddance, weirdo, vigilante, petroleum, billboard",
          "label": "context"
        }
      },
      {
        "from": "Player 2",
        "to": "GM",
        "timestamp": "2026-06-30T14:15:27.182823",
        "action": {
          "type": "get message",
          "content": "GUESS: courtroom, nomination, vigilante",
          "label": "response"
        }
      },
      {
        "from": "GM",
        "to": "GM",
        "timestamp": "2026-06-30T14:15:27.182876",
        "action": {
          "type": "guesses",
          "content": [
            "courtroom",
            "nomination",
            "vigilante"
          ]
        }
      },
      {
        "from": "GM",
        "to": "GM",
        "timestamp": "2026-06-30T14:15:27.182900",
        "action": {
          "type": "team revealed",
          "content": {
            "word": "courtroom",
            "assignment": "team"
          }
        }
      },
      {
        "from": "GM",
        "to": "GM",
        "timestamp": "2026-06-30T14:15:27.182920",
        "action": {
          "type": "target revealed",
          "content": {
            "word": "courtroom",
            "assignment": "team"
          }
        }
      },
      {
        "from": "GM",
        "to": "GM",
        "timestamp": "2026-06-30T14:15:27.182938",
        "action": {
          "type": "team revealed",
          "content": {
            "word": "nomination",
            "assignment": "team"
          }
        }
      },
      {
        "from": "GM",
        "to": "GM",
        "timestamp": "2026-06-30T14:15:27.182956",
        "action": {
          "type": "target revealed",
          "content": {
            "word": "nomination",
            "assignment": "team"
          }
        }
      },
      {
        "from": "GM",
        "to": "GM",
        "timestamp": "2026-06-30T14:15:27.182974",
        "action": {
          "type": "team revealed",
          "content": {
            "word": "vigilante",
            "assignment": "innocent"
          }
        }
      },
      {
        "from": "GM",
        "to": "GM",
        "timestamp": "2026-06-30T14:15:27.182992",
        "action": {
          "type": "turn end after",
          "content": "vigilante"
        }
      }
    ],
    [
      {
        "from": "GM",
        "to": "GM",
        "timestamp": "2026-06-30T14:15:27.183103",
        "action": {
          "type": "opponent revealed",
          "content": {
            "word": "mower",
            "assignment": "opponent"
          }
        }
      },
      {
        "from": "GM",
        "to": "GM",
        "timestamp": "2026-06-30T14:15:27.183130",
        "action": {
          "type": "board status",
          "content": {
            "hidden": {
              "team": [
                "terrain",
                "sailboat",
                "greenhouse",
                "bayou",
                "petroleum",
                "doorman",
                "migraine"
              ],
              "innocent": [
                "sincerity",
                "bacon",
                "riddance",
                "periscope",
                "apartment",
                "terrorism"
              ],
              "opponent": [
                "dime",
                "billboard",
                "bra",
                "weirdo",
                "burglary",
                "tanker",
                "nuisance"
              ],
              "assassin": [
                "bridesmaid"
              ]
            },
            "revealed": {
              "team": {
                "team": [
                  "courtroom",
                  "nomination"
                ],
                "innocent": [
                  "vigilante"
                ],
                "opponent": [],
                "assassin": []
              },
              "opponent": {
                "team": [],
                "innocent": [],
                "opponent": [
                  "mower"
                ],
                "assassin": []
              }
            }
          }
        }
      },
      {
        "from": "GM",
        "to": "Player 1",
        "timestamp": "2026-06-30T14:15:48.449869",
        "action": {
          "type": "send message",
          "content": "The words courtroom, nomination were guessed correctly. The word vigilante was guessed but is an innocent word. Your teammate's turn ended there.\nNow provide another clue relating to some of your remaining team words and a list of the related target words. Remember to start your clue with 'CLUE: ', put a new line, and start your comma-separated list of target words with 'TARGETS: '. Notice: some words have been removed from the lists compared to previous requests.\n\nYour remaining team words are: terrain, sailboat, greenhouse, bayou, petroleum, doorman, migraine.\nRemaining words for your opponent are: dime, billboard, mower, bra, weirdo, burglary, tanker, nuisance.\nRemaining distractor words are: sincerity, bacon, riddance, periscope, apartment, terrorism.\nRemaining kill words are: bridesmaid.",
          "label": "context"
        }
      },
      {
        "from": "Player 1",
        "to": "GM",
        "timestamp": "2026-06-30T14:15:48.449898",
        "action": {
          "type": "get message",
          "content": "CLUE: swamp\nTARGETS: bayou, terrain",
          "label": "response"
        }
      },
      {
        "from": "GM",
        "to": "GM",
        "timestamp": "2026-06-30T14:15:48.450092",
        "action": {
          "type": "clue",
          "content": "swamp"
        }
      },
      {
        "from": "GM",
        "to": "GM",
        "timestamp": "2026-06-30T14:15:48.450117",
        "action": {
          "type": "targets",
          "content": [
            "bayou",
            "terrain"
          ]
        }
      },
      {
        "from": "GM",
        "to": "GM",
        "timestamp": "2026-06-30T14:15:48.450137",
        "action": {
          "type": "word targeted",
          "content": {
            "word": "bayou",
            "assignment": "team"
          }
        }
      },
      {
        "from": "GM",
        "to": "GM",
        "timestamp": "2026-06-30T14:15:48.450155",
        "action": {
          "type": "word targeted",
          "content": {
            "word": "terrain",
            "assignment": "team"
          }
        }
      },
      {
        "from": "GM",
        "to": "Player 2",
        "timestamp": "2026-06-30T14:16:05.971408",
        "action": {
          "type": "send message",
          "content": "The words courtroom, nomination were guessed correctly. The word vigilante was guessed but is an innocent word. Your turn ended there.\nNow provide another comma-separated list of at least 1 and up to 2 words from the following list of words that best relate or are most closely associated with the word 'swamp'. Remember to start your answer with 'GUESS: '. Notice: some words have been removed from the list compared to previous requests.\n\nsincerity, greenhouse, doorman, migraine, sailboat, terrorism, terrain, nuisance, bayou, burglary, bridesmaid, apartment, periscope, dime, bra, bacon, tanker, riddance, weirdo, petroleum, billboard",
          "label": "context"
        }
      },
      {
        "from": "Player 2",
        "to": "GM",
        "timestamp": "2026-06-30T14:16:05.971423",
        "action": {
          "type": "get message",
          "content": "GUESS: bayou, terrain",
          "label": "response"
        }
      },
      {
        "from": "GM",
        "to": "GM",
        "timestamp": "2026-06-30T14:16:05.971511",
        "action": {
          "type": "guesses",
          "content": [
            "bayou",
            "terrain"
          ]
        }
      },
      {
        "from": "GM",
        "to": "GM",
        "timestamp": "2026-06-30T14:16:05.971548",
        "action": {
          "type": "team revealed",
          "content": {
            "word": "bayou",
            "assignment": "team"
          }
        }
      },
      {
        "from": "GM",
        "to": "GM",
        "timestamp": "2026-06-30T14:16:05.971570",
        "action": {
          "type": "target revealed",
          "content": {
            "word": "bayou",
            "assignment": "team"
          }
        }
      },
      {
        "from": "GM",
        "to": "GM",
        "timestamp": "2026-06-30T14:16:05.971591",
        "action": {
          "type": "team revealed",
          "content": {
            "word": "terrain",
            "assignment": "team"
          }
        }
      },
      {
        "from": "GM",
        "to": "GM",
        "timestamp": "2026-06-30T14:16:05.971608",
        "action": {
          "type": "target revealed",
          "content": {
            "word": "terrain",
            "assignment": "team"
          }
        }
      }
    ],
    [
      {
        "from": "GM",
        "to": "GM",
        "timestamp": "2026-06-30T14:16:05.971858",
        "action": {
          "type": "opponent revealed",
          "content": {
            "word": "dime",
            "assignment": "opponent"
          }
        }
      },
      {
        "from": "GM",
        "to": "GM",
        "timestamp": "2026-06-30T14:16:05.971888",
        "action": {
          "type": "board status",
          "content": {
            "hidden": {
              "team": [
                "sailboat",
                "greenhouse",
                "petroleum",
                "doorman",
                "migraine"
              ],
              "innocent": [
                "sincerity",
                "bacon",
                "riddance",
                "periscope",
                "apartment",
                "terrorism"
              ],
              "opponent": [
                "billboard",
                "bra",
                "weirdo",
                "burglary",
                "tanker",
                "nuisance"
              ],
              "assassin": [
                "bridesmaid"
              ]
            },
            "revealed": {
              "team": {
                "team": [
                  "courtroom",
                  "nomination",
                  "bayou",
                  "terrain"
                ],
                "innocent": [
                  "vigilante"
                ],
                "opponent": [],
                "assassin": []
              },
              "opponent": {
                "team": [],
                "innocent": [],
                "opponent": [
                  "mower",
                  "dime"
                ],
                "assassin": []
              }
            }
          }
        }
      },
      {
        "from": "GM",
        "to": "Player 1",
        "timestamp": "2026-06-30T14:16:23.238259",
        "action": {
          "type": "send message",
          "content": "The words bayou, terrain were guessed correctly. Your teammate's turn ended there.\nNow provide another clue relating to some of your remaining team words and a list of the related target words. Remember to start your clue with 'CLUE: ', put a new line, and start your comma-separated list of target words with 'TARGETS: '. Notice: some words have been removed from the lists compared to previous requests.\n\nYour remaining team words are: sailboat, greenhouse, petroleum, doorman, migraine.\nRemaining words for your opponent are: dime, billboard, bra, weirdo, burglary, tanker, nuisance.\nRemaining distractor words are: sincerity, bacon, riddance, periscope, apartment, terrorism.\nRemaining kill words are: bridesmaid.",
          "label": "context"
        }
      },
      {
        "from": "Player 1",
        "to": "GM",
        "timestamp": "2026-06-30T14:16:23.238277",
        "action": {
          "type": "get message",
          "content": "CLUE: oil\nTARGETS: petroleum, sailboat",
          "label": "response"
        }
      },
      {
        "from": "GM",
        "to": "GM",
        "timestamp": "2026-06-30T14:16:23.238420",
        "action": {
          "type": "clue",
          "content": "oil"
        }
      },
      {
        "from": "GM",
        "to": "GM",
        "timestamp": "2026-06-30T14:16:23.238442",
        "action": {
          "type": "targets",
          "content": [
            "petroleum",
            "sailboat"
          ]
        }
      },
      {
        "from": "GM",
        "to": "GM",
        "timestamp": "2026-06-30T14:16:23.238462",
        "action": {
          "type": "word targeted",
          "content": {
            "word": "petroleum",
            "assignment": "team"
          }
        }
      },
      {
        "from": "GM",
        "to": "GM",
        "timestamp": "2026-06-30T14:16:23.238482",
        "action": {
          "type": "word targeted",
          "content": {
            "word": "sailboat",
            "assignment": "team"
          }
        }
      },
      {
        "from": "GM",
        "to": "Player 2",
        "timestamp": "2026-06-30T14:16:38.791496",
        "action": {
          "type": "send message",
          "content": "The words bayou, terrain were guessed correctly. Your turn ended there.\nNow provide another comma-separated list of at least 1 and up to 2 words from the following list of words that best relate or are most closely associated with the word 'oil'. Remember to start your answer with 'GUESS: '. Notice: some words have been removed from the list compared to previous requests.\n\nsincerity, greenhouse, doorman, migraine, sailboat, terrorism, nuisance, burglary, bridesmaid, apartment, periscope, bra, bacon, tanker, riddance, weirdo, petroleum, billboard",
          "label": "context"
        }
      },
      {
        "from": "Player 2",
        "to": "GM",
        "timestamp": "2026-06-30T14:16:38.791515",
        "action": {
          "type": "get message",
          "content": "GUESS: petroleum, tanker",
          "label": "response"
        }
      },
      {
        "from": "GM",
        "to": "GM",
        "timestamp": "2026-06-30T14:16:38.791568",
        "action": {
          "type": "guesses",
          "content": [
            "petroleum",
            "tanker"
          ]
        }
      },
      {
        "from": "GM",
        "to": "GM",
        "timestamp": "2026-06-30T14:16:38.791594",
        "action": {
          "type": "team revealed",
          "content": {
            "word": "petroleum",
            "assignment": "team"
          }
        }
      },
      {
        "from": "GM",
        "to": "GM",
        "timestamp": "2026-06-30T14:16:38.791616",
        "action": {
          "type": "target revealed",
          "content": {
            "word": "petroleum",
            "assignment": "team"
          }
        }
      },
      {
        "from": "GM",
        "to": "GM",
        "timestamp": "2026-06-30T14:16:38.791636",
        "action": {
          "type": "team revealed",
          "content": {
            "word": "tanker",
            "assignment": "opponent"
          }
        }
      },
      {
        "from": "GM",
        "to": "GM",
        "timestamp": "2026-06-30T14:16:38.791654",
        "action": {
          "type": "turn end after",
          "content": "tanker"
        }
      }
    ],
    [
      {
        "from": "GM",
        "to": "GM",
        "timestamp": "2026-06-30T14:16:38.791800",
        "action": {
          "type": "opponent revealed",
          "content": {
            "word": "weirdo",
            "assignment": "opponent"
          }
        }
      },
      {
        "from": "GM",
        "to": "GM",
        "timestamp": "2026-06-30T14:16:38.791827",
        "action": {
          "type": "board status",
          "content": {
            "hidden": {
              "team": [
                "sailboat",
                "greenhouse",
                "doorman",
                "migraine"
              ],
              "innocent": [
                "sincerity",
                "bacon",
                "riddance",
                "periscope",
                "apartment",
                "terrorism"
              ],
              "opponent": [
                "billboard",
                "bra",
                "burglary",
                "nuisance"
              ],
              "assassin": [
                "bridesmaid"
              ]
            },
            "revealed": {
              "team": {
                "team": [
                  "courtroom",
                  "nomination",
                  "bayou",
                  "terrain",
                  "petroleum"
                ],
                "innocent": [
                  "vigilante"
                ],
                "opponent": [
                  "tanker"
                ],
                "assassin": []
              },
              "opponent": {
                "team": [],
                "innocent": [],
                "opponent": [
                  "mower",
                  "dime",
                  "weirdo"
                ],
                "assassin": []
              }
            }
          }
        }
      },
      {
        "from": "GM",
        "to": "Player 1",
        "timestamp": "2026-06-30T14:16:54.186815",
        "action": {
          "type": "send message",
          "content": "The word petroleum was guessed correctly. The word tanker was guessed but is an opponent word. Your teammate's turn ended there.\nNow provide another clue relating to some of your remaining team words and a list of the related target words. Remember to start your clue with 'CLUE: ', put a new line, and start your comma-separated list of target words with 'TARGETS: '. Notice: some words have been removed from the lists compared to previous requests.\n\nYour remaining team words are: sailboat, greenhouse, doorman, migraine.\nRemaining words for your opponent are: billboard, bra, weirdo, burglary, nuisance.\nRemaining distractor words are: sincerity, bacon, riddance, periscope, apartment, terrorism.\nRemaining kill words are: bridesmaid.",
          "label": "context"
        }
      },
      {
        "from": "Player 1",
        "to": "GM",
        "timestamp": "2026-06-30T14:16:54.186834",
        "action": {
          "type": "get message",
          "content": "CLUE: headache\nTARGETS: migraine, doorman",
          "label": "response"
        }
      },
      {
        "from": "GM",
        "to": "GM",
        "timestamp": "2026-06-30T14:16:54.186978",
        "action": {
          "type": "clue",
          "content": "headache"
        }
      },
      {
        "from": "GM",
        "to": "GM",
        "timestamp": "2026-06-30T14:16:54.187000",
        "action": {
          "type": "targets",
          "content": [
            "migraine",
            "doorman"
          ]
        }
      },
      {
        "from": "GM",
        "to": "GM",
        "timestamp": "2026-06-30T14:16:54.187020",
        "action": {
          "type": "word targeted",
          "content": {
            "word": "migraine",
            "assignment": "team"
          }
        }
      },
      {
        "from": "GM",
        "to": "GM",
        "timestamp": "2026-06-30T14:16:54.187039",
        "action": {
          "type": "word targeted",
          "content": {
            "word": "doorman",
            "assignment": "team"
          }
        }
      },
      {
        "from": "GM",
        "to": "Player 2",
        "timestamp": "2026-06-30T14:17:08.981529",
        "action": {
          "type": "send message",
          "content": "The word petroleum was guessed correctly. The word tanker was guessed but is an opponent word. Your turn ended there.\nNow provide another comma-separated list of at least 1 and up to 2 words from the following list of words that best relate or are most closely associated with the word 'headache'. Remember to start your answer with 'GUESS: '. Notice: some words have been removed from the list compared to previous requests.\n\nsincerity, greenhouse, doorman, migraine, sailboat, terrorism, nuisance, burglary, bridesmaid, apartment, periscope, bra, bacon, riddance, billboard",
          "label": "context"
        }
      },
      {
        "from": "Player 2",
        "to": "GM",
        "timestamp": "2026-06-30T14:17:08.981545",
        "action": {
          "type": "get message",
          "content": "GUESS: migraine",
          "label": "response"
        }
      },
      {
        "from": "GM",
        "to": "GM",
        "timestamp": "2026-06-30T14:17:08.981611",
        "action": {
          "type": "guesses",
          "content": [
            "migraine"
          ]
        }
      },
      {
        "from": "GM",
        "to": "GM",
        "timestamp": "2026-06-30T14:17:08.981648",
        "action": {
          "type": "team revealed",
          "content": {
            "word": "migraine",
            "assignment": "team"
          }
        }
      },
      {
        "from": "GM",
        "to": "GM",
        "timestamp": "2026-06-30T14:17:08.981671",
        "action": {
          "type": "target revealed",
          "content": {
            "word": "migraine",
            "assignment": "team"
          }
        }
      }
    ],
    [
      {
        "from": "GM",
        "to": "GM",
        "timestamp": "2026-06-30T14:17:08.981953",
        "action": {
          "type": "opponent revealed",
          "content": {
            "word": "billboard",
            "assignment": "opponent"
          }
        }
      },
      {
        "from": "GM",
        "to": "GM",
        "timestamp": "2026-06-30T14:17:08.981982",
        "action": {
          "type": "board status",
          "content": {
            "hidden": {
              "team": [
                "sailboat",
                "greenhouse",
                "doorman"
              ],
              "innocent": [
                "sincerity",
                "bacon",
                "riddance",
                "periscope",
                "apartment",
                "terrorism"
              ],
              "opponent": [
                "bra",
                "burglary",
                "nuisance"
              ],
              "assassin": [
                "bridesmaid"
              ]
            },
            "revealed": {
              "team": {
                "team": [
                  "courtroom",
                  "nomination",
                  "bayou",
                  "terrain",
                  "petroleum",
                  "migraine"
                ],
                "innocent": [
                  "vigilante"
                ],
                "opponent": [
                  "tanker"
                ],
                "assassin": []
              },
              "opponent": {
                "team": [],
                "innocent": [],
                "opponent": [
                  "mower",
                  "dime",
                  "weirdo",
                  "billboard"
                ],
                "assassin": []
              }
            }
          }
        }
      },
      {
        "from": "GM",
        "to": "Player 1",
        "timestamp": "2026-06-30T14:17:23.401702",
        "action": {
          "type": "send message",
          "content": "The word migraine was guessed correctly. Your teammate's turn ended there.\nNow provide another clue relating to some of your remaining team words and a list of the related target words. Remember to start your clue with 'CLUE: ', put a new line, and start your comma-separated list of target words with 'TARGETS: '. Notice: some words have been removed from the lists compared to previous requests.\n\nYour remaining team words are: sailboat, greenhouse, doorman.\nRemaining words for your opponent are: billboard, bra, burglary, nuisance.\nRemaining distractor words are: sincerity, bacon, riddance, periscope, apartment, terrorism.\nRemaining kill words are: bridesmaid.",
          "label": "context"
        }
      },
      {
        "from": "Player 1",
        "to": "GM",
        "timestamp": "2026-06-30T14:17:23.401717",
        "action": {
          "type": "get message",
          "content": "CLUE: house\nTARGETS: greenhouse, doorman",
          "label": "response"
        }
      },
      {
        "from": "GM",
        "to": "GM",
        "timestamp": "2026-06-30T14:17:23.401931",
        "action": {
          "type": "clue",
          "content": "house"
        }
      },
      {
        "from": "GM",
        "to": "GM",
        "timestamp": "2026-06-30T14:17:23.401967",
        "action": {
          "type": "targets",
          "content": [
            "greenhouse",
            "doorman"
          ]
        }
      },
      {
        "from": "GM",
        "to": "GM",
        "timestamp": "2026-06-30T14:17:23.401993",
        "action": {
          "type": "word targeted",
          "content": {
            "word": "greenhouse",
            "assignment": "team"
          }
        }
      },
      {
        "from": "GM",
        "to": "GM",
        "timestamp": "2026-06-30T14:17:23.402013",
        "action": {
          "type": "word targeted",
          "content": {
            "word": "doorman",
            "assignment": "team"
          }
        }
      },
      {
        "from": "GM",
        "to": "Player 2",
        "timestamp": "2026-06-30T14:17:34.856952",
        "action": {
          "type": "send message",
          "content": "The word migraine was guessed correctly. Your turn ended there.\nNow provide another comma-separated list of at least 1 and up to 2 words from the following list of words that best relate or are most closely associated with the word 'house'. Remember to start your answer with 'GUESS: '. Notice: some words have been removed from the list compared to previous requests.\n\nsincerity, greenhouse, doorman, sailboat, terrorism, nuisance, burglary, bridesmaid, apartment, periscope, bra, bacon, riddance",
          "label": "context"
        }
      },
      {
        "from": "Player 2",
        "to": "GM",
        "timestamp": "2026-06-30T14:17:34.856969",
        "action": {
          "type": "get message",
          "content": "GUESS: greenhouse, apartment",
          "label": "response"
        }
      },
      {
        "from": "GM",
        "to": "GM",
        "timestamp": "2026-06-30T14:17:34.857022",
        "action": {
          "type": "guesses",
          "content": [
            "greenhouse",
            "apartment"
          ]
        }
      },
      {
        "from": "GM",
        "to": "GM",
        "timestamp": "2026-06-30T14:17:34.857047",
        "action": {
          "type": "team revealed",
          "content": {
            "word": "greenhouse",
            "assignment": "team"
          }
        }
      },
      {
        "from": "GM",
        "to": "GM",
        "timestamp": "2026-06-30T14:17:34.857067",
        "action": {
          "type": "target revealed",
          "content": {
            "word": "greenhouse",
            "assignment": "team"
          }
        }
      },
      {
        "from": "GM",
        "to": "GM",
        "timestamp": "2026-06-30T14:17:34.857087",
        "action": {
          "type": "team revealed",
          "content": {
            "word": "apartment",
            "assignment": "innocent"
          }
        }
      },
      {
        "from": "GM",
        "to": "GM",
        "timestamp": "2026-06-30T14:17:34.857105",
        "action": {
          "type": "turn end after",
          "content": "apartment"
        }
      }
    ],
    [
      {
        "from": "GM",
        "to": "GM",
        "timestamp": "2026-06-30T14:17:34.857239",
        "action": {
          "type": "opponent revealed",
          "content": {
            "word": "bra",
            "assignment": "opponent"
          }
        }
      },
      {
        "from": "GM",
        "to": "GM",
        "timestamp": "2026-06-30T14:17:34.857266",
        "action": {
          "type": "board status",
          "content": {
            "hidden": {
              "team": [
                "sailboat",
                "doorman"
              ],
              "innocent": [
                "sincerity",
                "bacon",
                "riddance",
                "periscope",
                "terrorism"
              ],
              "opponent": [
                "burglary",
                "nuisance"
              ],
              "assassin": [
                "bridesmaid"
              ]
            },
            "revealed": {
              "team": {
                "team": [
                  "courtroom",
                  "nomination",
                  "bayou",
                  "terrain",
                  "petroleum",
                  "migraine",
                  "greenhouse"
                ],
                "innocent": [
                  "vigilante",
                  "apartment"
                ],
                "opponent": [
                  "tanker"
                ],
                "assassin": []
              },
              "opponent": {
                "team": [],
                "innocent": [],
                "opponent": [
                  "mower",
                  "dime",
                  "weirdo",
                  "billboard",
                  "bra"
                ],
                "assassin": []
              }
            }
          }
        }
      },
      {
        "from": "GM",
        "to": "Player 1",
        "timestamp": "2026-06-30T14:17:45.437975",
        "action": {
          "type": "send message",
          "content": "The word greenhouse was guessed correctly. The word apartment was guessed but is an innocent word. Your teammate's turn ended there.\nNow provide another clue relating to some of your remaining team words and a list of the related target words. Remember to start your clue with 'CLUE: ', put a new line, and start your comma-separated list of target words with 'TARGETS: '. Notice: some words have been removed from the lists compared to previous requests.\n\nYour remaining team words are: sailboat, doorman.\nRemaining words for your opponent are: bra, burglary, nuisance.\nRemaining distractor words are: sincerity, bacon, riddance, periscope, terrorism.\nRemaining kill words are: bridesmaid.",
          "label": "context"
        }
      },
      {
        "from": "Player 1",
        "to": "GM",
        "timestamp": "2026-06-30T14:17:45.437992",
        "action": {
          "type": "get message",
          "content": "CLUE: harbor\nTARGETS: sailboat, doorman",
          "label": "response"
        }
      },
      {
        "from": "GM",
        "to": "GM",
        "timestamp": "2026-06-30T14:17:45.438128",
        "action": {
          "type": "clue",
          "content": "harbor"
        }
      },
      {
        "from": "GM",
        "to": "GM",
        "timestamp": "2026-06-30T14:17:45.438150",
        "action": {
          "type": "targets",
          "content": [
            "sailboat",
            "doorman"
          ]
        }
      },
      {
        "from": "GM",
        "to": "GM",
        "timestamp": "2026-06-30T14:17:45.438170",
        "action": {
          "type": "word targeted",
          "content": {
            "word": "sailboat",
            "assignment": "team"
          }
        }
      },
      {
        "from": "GM",
        "to": "GM",
        "timestamp": "2026-06-30T14:17:45.438189",
        "action": {
          "type": "word targeted",
          "content": {
            "word": "doorman",
            "assignment": "team"
          }
        }
      },
      {
        "from": "GM",
        "to": "Player 2",
        "timestamp": "2026-06-30T14:17:55.466660",
        "action": {
          "type": "send message",
          "content": "The word greenhouse was guessed correctly. The word apartment was guessed but is an innocent word. Your turn ended there.\nNow provide another comma-separated list of at least 1 and up to 2 words from the following list of words that best relate or are most closely associated with the word 'harbor'. Remember to start your answer with 'GUESS: '. Notice: some words have been removed from the list compared to previous requests.\n\nsincerity, doorman, sailboat, terrorism, nuisance, burglary, bridesmaid, periscope, bacon, riddance",
          "label": "context"
        }
      },
      {
        "from": "Player 2",
        "to": "GM",
        "timestamp": "2026-06-30T14:17:55.466676",
        "action": {
          "type": "get message",
          "content": "GUESS: sailboat, periscope",
          "label": "response"
        }
      },
      {
        "from": "GM",
        "to": "GM",
        "timestamp": "2026-06-30T14:17:55.466773",
        "action": {
          "type": "guesses",
          "content": [
            "sailboat",
            "periscope"
          ]
        }
      },
      {
        "from": "GM",
        "to": "GM",
        "timestamp": "2026-06-30T14:17:55.466820",
        "action": {
          "type": "team revealed",
          "content": {
            "word": "sailboat",
            "assignment": "team"
          }
        }
      },
      {
        "from": "GM",
        "to": "GM",
        "timestamp": "2026-06-30T14:17:55.466844",
        "action": {
          "type": "target revealed",
          "content": {
            "word": "sailboat",
            "assignment": "team"
          }
        }
      },
      {
        "from": "GM",
        "to": "GM",
        "timestamp": "2026-06-30T14:17:55.466865",
        "action": {
          "type": "team revealed",
          "content": {
            "word": "periscope",
            "assignment": "innocent"
          }
        }
      },
      {
        "from": "GM",
        "to": "GM",
        "timestamp": "2026-06-30T14:17:55.466883",
        "action": {
          "type": "turn end after",
          "content": "periscope"
        }
      }
    ],
    [
      {
        "from": "GM",
        "to": "GM",
        "timestamp": "2026-06-30T14:17:55.467183",
        "action": {
          "type": "opponent revealed",
          "content": {
            "word": "burglary",
            "assignment": "opponent"
          }
        }
      },
      {
        "from": "GM",
        "to": "GM",
        "timestamp": "2026-06-30T14:17:55.467213",
        "action": {
          "type": "board status",
          "content": {
            "hidden": {
              "team": [
                "doorman"
              ],
              "innocent": [
                "sincerity",
                "bacon",
                "riddance",
                "terrorism"
              ],
              "opponent": [
                "nuisance"
              ],
              "assassin": [
                "bridesmaid"
              ]
            },
            "revealed": {
              "team": {
                "team": [
                  "courtroom",
                  "nomination",
                  "bayou",
                  "terrain",
                  "petroleum",
                  "migraine",
                  "greenhouse",
                  "sailboat"
                ],
                "innocent": [
                  "vigilante",
                  "apartment",
                  "periscope"
                ],
                "opponent": [
                  "tanker"
                ],
                "assassin": []
              },
              "opponent": {
                "team": [],
                "innocent": [],
                "opponent": [
                  "mower",
                  "dime",
                  "weirdo",
                  "billboard",
                  "bra",
                  "burglary"
                ],
                "assassin": []
              }
            }
          }
        }
      },
      {
        "from": "GM",
        "to": "Player 1",
        "timestamp": "2026-06-30T14:18:03.883141",
        "action": {
          "type": "send message",
          "content": "The word sailboat was guessed correctly. The word periscope was guessed but is an innocent word. Your teammate's turn ended there.\nNow provide another clue relating to some of your remaining team words and a list of the related target words. Remember to start your clue with 'CLUE: ', put a new line, and start your comma-separated list of target words with 'TARGETS: '. Notice: some words have been removed from the lists compared to previous requests.\n\nYour remaining team words are: doorman.\nRemaining words for your opponent are: burglary, nuisance.\nRemaining distractor words are: sincerity, bacon, riddance, terrorism.\nRemaining kill words are: bridesmaid.",
          "label": "context"
        }
      },
      {
        "from": "Player 1",
        "to": "GM",
        "timestamp": "2026-06-30T14:18:03.883180",
        "action": {
          "type": "get message",
          "content": "CLUE: hotel\nTARGETS: doorman",
          "label": "response"
        }
      },
      {
        "from": "GM",
        "to": "GM",
        "timestamp": "2026-06-30T14:18:03.883400",
        "action": {
          "type": "clue",
          "content": "hotel"
        }
      },
      {
        "from": "GM",
        "to": "GM",
        "timestamp": "2026-06-30T14:18:03.883448",
        "action": {
          "type": "targets",
          "content": [
            "doorman"
          ]
        }
      },
      {
        "from": "GM",
        "to": "GM",
        "timestamp": "2026-06-30T14:18:03.883490",
        "action": {
          "type": "word targeted",
          "content": {
            "word": "doorman",
            "assignment": "team"
          }
        }
      },
      {
        "from": "GM",
        "to": "Player 2",
        "timestamp": "2026-06-30T14:18:09.483530",
        "action": {
          "type": "send message",
          "content": "The word sailboat was guessed correctly. The word periscope was guessed but is an innocent word. Your turn ended there.\nNow provide another comma-separated list of at least 1 and up to 1 words from the following list of words that best relate or are most closely associated with the word 'hotel'. Remember to start your answer with 'GUESS: '. Notice: some words have been removed from the list compared to previous requests.\n\nsincerity, doorman, terrorism, nuisance, bridesmaid, bacon, riddance",
          "label": "context"
        }
      },
      {
        "from": "Player 2",
        "to": "GM",
        "timestamp": "2026-06-30T14:18:09.483552",
        "action": {
          "type": "get message",
          "content": "GUESS: doorman",
          "label": "response"
        }
      },
      {
        "from": "GM",
        "to": "GM",
        "timestamp": "2026-06-30T14:18:09.483607",
        "action": {
          "type": "guesses",
          "content": [
            "doorman"
          ]
        }
      },
      {
        "from": "GM",
        "to": "GM",
        "timestamp": "2026-06-30T14:18:09.483636",
        "action": {
          "type": "team revealed",
          "content": {
            "word": "doorman",
            "assignment": "team"
          }
        }
      },
      {
        "from": "GM",
        "to": "GM",
        "timestamp": "2026-06-30T14:18:09.483659",
        "action": {
          "type": "target revealed",
          "content": {
            "word": "doorman",
            "assignment": "team"
          }
        }
      },
      {
        "from": "GM",
        "to": "GM",
        "timestamp": "2026-06-30T14:18:09.483774",
        "action": {
          "type": "game end",
          "content": "team has won"
        }
      }
    ]
  ],
  "board end status": {
    "hidden": {
      "team": [],
      "innocent": [
        "sincerity",
        "bacon",
        "riddance",
        "terrorism"
      ],
      "opponent": [
        "nuisance"
      ],
      "assassin": [
        "bridesmaid"
      ]
    },
    "revealed": {
      "team": {
        "team": [
          "courtroom",
          "nomination",
          "bayou",
          "terrain",
          "petroleum",
          "migraine",
          "greenhouse",
          "sailboat",
          "doorman"
        ],
        "innocent": [
          "vigilante",
          "apartment",
          "periscope"
        ],
        "opponent": [
          "tanker"
        ],
        "assassin": []
      },
      "opponent": {
        "team": [],
        "innocent": [],
        "opponent": [
          "mower",
          "dime",
          "weirdo",
          "billboard",
          "bra",
          "burglary"
        ],
        "assassin": []
      }
    }
  },
  "Number of turns": 8,
  "Aborted": false,
  "Lose": false,
  "Game ended through assassin": false,
  "Request Count": 14,
  "Parsed Request Count": 14,
  "Violated Request Count": 0,
  "Cluegiver engaged flags": {
    "IGNORE RAMBLING": 0,
    "IGNORE FALSE TARGETS OR GUESSES": 0,
    "REPROMPT ON ERROR": 0,
    "STRIP WORDS": 0,
    "IGNORE NUMBER OF TARGETS": 0
  },
  "Guesser engaged flags": {
    "IGNORE RAMBLING": 0,
    "IGNORE FALSE TARGETS OR GUESSES": 0,
    "REPROMPT ON ERROR": 0,
    "STRIP WORDS": 0,
    "IGNORE NUMBER OF TARGETS": 0
  }
}